pycritter/__init__.py
pycritter/pycritter.py
PyCritter-0.0.2.dist-info/LICENSE
PyCritter-0.0.2.dist-info/METADATA
PyCritter-0.0.2.dist-info/WHEEL
PyCritter-0.0.2.dist-info/top_level.txt
PyCritter-0.0.2.dist-info/RECORD
